regex2csv/__init__.py
regex2csv/main.py
regex2csv-0.0.1.dist-info/LICENSE
regex2csv-0.0.1.dist-info/METADATA
regex2csv-0.0.1.dist-info/WHEEL
regex2csv-0.0.1.dist-info/entry_points.txt
regex2csv-0.0.1.dist-info/top_level.txt
regex2csv-0.0.1.dist-info/RECORD
