Metadata-Version: 2.1
Name: regex2csv
Version: 0.0.1
Summary: A Python script that extracts regex capture groups and puts into a CSV file.
Author-email: Lucas Marcolongo <lucas@marcolongo.dev>
License: GNU GENERAL PUBLIC LICENSE
Project-URL: Source, https://github.com/marcolongol/regex2csv
License-File: LICENSE
